launchdman/__init__.py
launchdman/debug.py
launchdman/test.py
launchdman/test1.py
launchdman-0.1.2.dist-info/DESCRIPTION.rst
launchdman-0.1.2.dist-info/METADATA
launchdman-0.1.2.dist-info/RECORD
launchdman-0.1.2.dist-info/WHEEL
launchdman-0.1.2.dist-info/metadata.json
launchdman-0.1.2.dist-info/top_level.txt
