Metadata-Version: 2.0
Name: launchdman
Version: 0.1.2
Summary: The launchd parser and manager for Python
Home-page: https://github.com/casouri/launchdman
Author: Yuan Fu
Author-email: yuan.k.fu@gmail.com
License: MIT
Download-URL: https://github.com/casouri/launchdman/archive/0.1.tar.gz
Platform: UNKNOWN
Requires-Python: >=3
